CUCMLib/AXLAPI.wsdl
CUCMLib/AXLEnums.xsd
CUCMLib/AXLSoap.xsd
CUCMLib/__init__.py
CUCMLib/partition.py
CUCMLib/phone.py
CUCMLib-0.1.9.dist-info/METADATA
CUCMLib-0.1.9.dist-info/WHEEL
CUCMLib-0.1.9.dist-info/top_level.txt
CUCMLib-0.1.9.dist-info/RECORD
