Metadata-Version: 2.1
Name: CUCMLib
Version: 0.1.9
Summary: CUCM ile etkileşim için bir kütüphane
Author: SafaBasdemir
Author-email: safabasdemir@gmail.com
Classifier: Programming Language :: Python :: 3
Classifier: License :: OSI Approved :: MIT License
Classifier: Operating System :: OS Independent
Requires-Python: >=3.6
Requires-Dist: zeep
Requires-Dist: pandas
